<?xml version="1.0" encoding="utf-8"?>
<root>
  <entity name="BannerDTO" fullName="TpFinalTDP2015.Service.DTO.BannerDTO">
    <language name="English" code="en">
      <property name="CreationDate">
        <text>Creation Date</text>
        <enable>false</enable>
      </property>
      <property name="Id">
        <text>ID</text>
        <enable>true</enable>
      </property>
      <property name="ModificationDate">
        <text>Last Modified</text>
        <enable>true</enable>
      </property>
      <property name="Name">
        <text>Name</text>
        <enable>true</enable>
      </property>
      <property name="Description">
        <text>Description</text>
        <enable>true</enable>
      </property>
      <property name="ActiveIntervals">
        <text>ActiveIntervals</text>
        <enable>false</enable>
      </property>
      <property name="Items">
        <text>Items</text>
        <enable>false</enable>
      </property>
    </language>
    <language name="Spanish (Argentina)" code="es-AR">
      <property name="CreationDate">
        <text>Fecha de Creacion</text>
        <enable>false</enable>
      </property>
      <property name="Id">
        <text>Id</text>
        <enable>true</enable>ID
      </property>
      <property name="ModificationDate">
        <text>Ultima Modificacion</text>
        <enable>true</enable>
      </property>
      <property name="Name">
        <text>Nombre</text>
        <enable>true</enable>
      </property>
      <property name="Description">
        <text>Descripcion</text>
        <enable>true</enable>
      </property>
      <property name="ActiveIntervals">
        <text>Intervalos Activos</text>
        <enable>false</enable>
      </property>
      <property name="Items">
        <text>Items</text>
        <enable>false</enable>
      </property>
    </language>
  </entity>
</root>